skorecard/__init__.py
skorecard/bucket_mapping.py
skorecard/datasets.py
skorecard/features_bucket_mapping.py
skorecard/skorecard.py
skorecard/apps/__init__.py
skorecard/apps/app_callbacks.py
skorecard/apps/app_layout.py
skorecard/apps/app_utils.py
skorecard/apps/assets/united-bootstrap.min.css
skorecard/bucketers/__init__.py
skorecard/bucketers/base_bucketer.py
skorecard/bucketers/bucketers.py
skorecard/data/UCI_Credit_Card.zip
skorecard/linear_model/__init__.py
skorecard/linear_model/linear_model.py
skorecard/metrics/__init__.py
skorecard/metrics/metrics.py
skorecard/pipeline/__init__.py
skorecard/pipeline/bucketing_process.py
skorecard/pipeline/pipeline.py
skorecard/preprocessing/_WoEEncoder.py
skorecard/preprocessing/__init__.py
skorecard/preprocessing/preprocessing.py
skorecard/reporting/__init__.py
skorecard/reporting/plotting.py
skorecard/reporting/report.py
skorecard/rescale/__init__.py
skorecard/rescale/rescale.py
skorecard/utils/__init__.py
skorecard/utils/arrayfuncs.py
skorecard/utils/dataframe.py
skorecard/utils/exceptions.py
skorecard/utils/validation.py
skorecard-1.6.9.dist-info/LICENSE
skorecard-1.6.9.dist-info/METADATA
skorecard-1.6.9.dist-info/WHEEL
skorecard-1.6.9.dist-info/top_level.txt
skorecard-1.6.9.dist-info/RECORD
