Metadata-Version: 2.1
Name: skorecard
Version: 1.6.9
Summary: Tools for building scorecard models in python, with a sklearn-compatible API
Author-email: "ING Bank N.V." <anilkumar.panda@ing.com>
License: The MIT License (MIT)
Project-URL: Homepage, https://ing-bank.github.io/skorecard/
Project-URL: Documentation, https://ing-bank.github.io/skorecard/api/bucketers/OptimalBucketer/
Project-URL: Repository, https://github.com/ing-bank/skorecard.git
Project-URL: Changelog, https://github.com/ing-bank/skorecard/blob/main/CHANGELOG.md
Classifier: License :: OSI Approved :: MIT License
Classifier: Operating System :: OS Independent
Classifier: Programming Language :: Python
Classifier: Programming Language :: Python :: 3
Classifier: Programming Language :: Python :: 3.9
Classifier: Programming Language :: Python :: 3.10
Classifier: Programming Language :: Python :: 3.11
Classifier: Programming Language :: Python :: 3.12
Classifier: Programming Language :: Python :: 3 :: Only
Requires-Python: >=3.9
License-File: LICENSE
Requires-Dist: scipy >=1.5.2
Requires-Dist: numpy <2.0.0,>=1.19.5
Requires-Dist: pandas >=1.5.3
Requires-Dist: scikit-learn >=0.23.2
Requires-Dist: pyyaml
Requires-Dist: category-encoders >=2.2.2
Requires-Dist: optbinning >=0.8.0
Provides-Extra: all
Requires-Dist: skorecard[dashboard,dev,docs,reporting] ; extra == 'all'
Provides-Extra: dashboard
Requires-Dist: dash >=1.21.0 ; extra == 'dashboard'
Requires-Dist: jupyter-dash >=0.4.0 ; extra == 'dashboard'
Requires-Dist: dash-bootstrap-components >=0.13 ; extra == 'dashboard'
Provides-Extra: dev
Requires-Dist: black >=19.10b0 ; extra == 'dev'
Requires-Dist: pytest >=6.0.0 ; extra == 'dev'
Requires-Dist: pytest-cov >=2.10.0 ; extra == 'dev'
Requires-Dist: pyflakes >=3.0.1 ; extra == 'dev'
Requires-Dist: mypy >=0.770 ; extra == 'dev'
Requires-Dist: pre-commit >=2.7.1 ; extra == 'dev'
Requires-Dist: isort >=5.12.0 ; extra == 'dev'
Requires-Dist: codespell >=2.2.4 ; extra == 'dev'
Requires-Dist: ruff >=0.2.2 ; extra == 'dev'
Requires-Dist: types-PyYAML >=6.0.12.10 ; extra == 'dev'
Requires-Dist: types-six >=1.16.21.8 ; extra == 'dev'
Requires-Dist: types-decorator >=5.1.8.3 ; extra == 'dev'
Provides-Extra: docs
Requires-Dist: mkdocs >=1.1.2 ; extra == 'docs'
Requires-Dist: mkdocs-material >=7.1 ; extra == 'docs'
Requires-Dist: mkdocstrings >=0.13.2 ; extra == 'docs'
Requires-Dist: mknotebooks >=0.7.0 ; extra == 'docs'
Requires-Dist: mkdocs-git-revision-date-localized-plugin >=0.7.2 ; extra == 'docs'
Requires-Dist: mkdocstrings-python >=1.1.2 ; extra == 'docs'
Provides-Extra: reporting
Requires-Dist: plotly >=4.14.3 ; extra == 'reporting'
